odoo10_addon_account_invoice_triple_discount-10.0.1.0.2-nspkg.pth
odoo/addons/account_invoice_triple_discount/README.rst
odoo/addons/account_invoice_triple_discount/__init__.py
odoo/addons/account_invoice_triple_discount/__manifest__.py
odoo/addons/account_invoice_triple_discount/i18n/account_invoice_triple_discount.pot
odoo/addons/account_invoice_triple_discount/i18n/ar.po
odoo/addons/account_invoice_triple_discount/i18n/bg.po
odoo/addons/account_invoice_triple_discount/i18n/bs.po
odoo/addons/account_invoice_triple_discount/i18n/ca.po
odoo/addons/account_invoice_triple_discount/i18n/cs.po
odoo/addons/account_invoice_triple_discount/i18n/de.po
odoo/addons/account_invoice_triple_discount/i18n/el_GR.po
odoo/addons/account_invoice_triple_discount/i18n/en_GB.po
odoo/addons/account_invoice_triple_discount/i18n/es.po
odoo/addons/account_invoice_triple_discount/i18n/es_CR.po
odoo/addons/account_invoice_triple_discount/i18n/es_EC.po
odoo/addons/account_invoice_triple_discount/i18n/es_ES.po
odoo/addons/account_invoice_triple_discount/i18n/es_MX.po
odoo/addons/account_invoice_triple_discount/i18n/es_PE.po
odoo/addons/account_invoice_triple_discount/i18n/et.po
odoo/addons/account_invoice_triple_discount/i18n/fi.po
odoo/addons/account_invoice_triple_discount/i18n/fr.po
odoo/addons/account_invoice_triple_discount/i18n/fr_CA.po
odoo/addons/account_invoice_triple_discount/i18n/fr_CH.po
odoo/addons/account_invoice_triple_discount/i18n/gl.po
odoo/addons/account_invoice_triple_discount/i18n/hr.po
odoo/addons/account_invoice_triple_discount/i18n/hr_HR.po
odoo/addons/account_invoice_triple_discount/i18n/hu.po
odoo/addons/account_invoice_triple_discount/i18n/id.po
odoo/addons/account_invoice_triple_discount/i18n/it.po
odoo/addons/account_invoice_triple_discount/i18n/ja.po
odoo/addons/account_invoice_triple_discount/i18n/lt.po
odoo/addons/account_invoice_triple_discount/i18n/mk.po
odoo/addons/account_invoice_triple_discount/i18n/mn.po
odoo10_addon_account_invoice_triple_discount-10.0.1.0.2.dist-info/METADATA
odoo10_addon_account_invoice_triple_discount-10.0.1.0.2.dist-info/WHEEL
odoo10_addon_account_invoice_triple_discount-10.0.1.0.2.dist-info/namespace_packages.txt
odoo10_addon_account_invoice_triple_discount-10.0.1.0.2.dist-info/top_level.txt
odoo10_addon_account_invoice_triple_discount-10.0.1.0.2.dist-info/RECORD
